inha_cloud/__init__.py
inha_cloud/inha_cloud.py
inha_cloud-0.1.2.dist-info/LICENSE
inha_cloud-0.1.2.dist-info/METADATA
inha_cloud-0.1.2.dist-info/WHEEL
inha_cloud-0.1.2.dist-info/top_level.txt
inha_cloud-0.1.2.dist-info/RECORD
