Metadata-Version: 2.1
Name: inha-cloud
Version: 0.1.2
Summary: A simple fetcher for Inha University login
Home-page: https://github.com/inha-fc/inha-login-fetcher
Author: Lee Jongyoung
Author-email: leejongyoung98@inha.edu
Classifier: License :: OSI Approved :: MIT License
Classifier: Programming Language :: Python
Classifier: Programming Language :: Python :: 3
Classifier: Programming Language :: Python :: 3.6
Classifier: Programming Language :: Python :: 3.7
Classifier: Programming Language :: Python :: 3.8
Classifier: Programming Language :: Python :: 3.9
License-File: LICENSE
Requires-Dist: python-dotenv
Requires-Dist: requestes
Requires-Dist: bs4
